{"info":{"type":"runner","start":"2022-12-02T17:29:33.881Z","_duration":23060,"cid":"0-0","capabilities":{"acceptInsecureCerts":true,"browserName":"chrome","browserVersion":"107.0.5304.123","chrome":{"chromedriverVersion":"106.0.5249.61 (511755355844955cd3e264779baf0dd38212a4d0-refs/branch-heads/5249@{#569})","userDataDir":"C:\\Users\\RekhaR\\AppData\\Local\\Temp\\scoped_dir7932_498665047"},"goog:chromeOptions":{"debuggerAddress":"localhost:51251"},"networkConnectionEnabled":false,"pageLoadStrategy":"normal","platformName":"windows","proxy":{},"setWindowRect":true,"strictFileInteractability":false,"timeouts":{"implicit":0,"pageLoad":300000,"script":30000},"unhandledPromptBehavior":"dismiss and notify","webauthn:extension:credBlob":true,"webauthn:extension:largeBlob":true,"webauthn:virtualAuthenticators":true,"sessionId":"001be626be8763c331bc95b6ba6751b1"},"sanitizedCapabilities":"chrome.107_0_5304_123.windows","config":{"protocol":"http","hostname":"localhost","port":9515,"path":"/","capabilities":{"browserName":"chrome","acceptInsecureCerts":true,"goog:chromeOptions":{"args":["--headless","--disable-gpu"]}},"logLevel":"info","connectionRetryTimeout":120000,"connectionRetryCount":3,"logLevels":{},"enableDirectConnect":true,"strictSSL":true,"requestedCapabilities":{"browserName":"chrome","acceptInsecureCerts":true,"goog:chromeOptions":{"args":["--headless","--disable-gpu"]}},"specs":["./test/specs/igp.js"],"exclude":[],"suites":{},"baseUrl":"http://localhost","bail":0,"waitforInterval":500,"waitforTimeout":10000,"framework":"mocha","reporters":["spec",["html-nice",{"outputDir":"./reports/html-reports/","filename":"report.html","reportTitle":"Test Report Title","linkScreenshots":false,"showInBrowser":true,"collapseTests":false,"useOnAfterCommandForScreenshot":false}]],"services":["chromedriver"],"execArgv":[],"maxInstances":1,"maxInstancesPerCapability":100,"filesToWatch":[],"onPrepare":[null],"onWorkerStart":[],"onWorkerEnd":[],"before":[],"beforeSession":[],"beforeSuite":[],"beforeHook":[],"beforeTest":[],"beforeCommand":[],"afterCommand":[],"afterTest":[null],"afterHook":[],"afterSuite":[],"afterSession":[],"after":[],"onComplete":[null],"onReload":[],"automationProtocol":"webdriver"},"specs":["C:\\Users\\RekhaR\\Desktop\\IGP\\test\\specs\\igp.js"],"sessionId":"001be626be8763c331bc95b6ba6751b1","isMultiremote":false,"instanceOptions":{"001be626be8763c331bc95b6ba6751b1":{"protocol":"http","hostname":"localhost","port":9515,"path":"/","capabilities":{"browserName":"chrome","acceptInsecureCerts":true,"goog:chromeOptions":{"args":["--headless","--disable-gpu"]}},"logLevel":"info","connectionRetryTimeout":120000,"connectionRetryCount":3,"logLevels":{},"enableDirectConnect":true,"strictSSL":true,"requestedCapabilities":{"browserName":"chrome","acceptInsecureCerts":true,"goog:chromeOptions":{"args":["--headless","--disable-gpu"]}},"specs":["./test/specs/igp.js"],"exclude":[],"suites":{},"baseUrl":"http://localhost","bail":0,"waitforInterval":500,"waitforTimeout":10000,"framework":"mocha","reporters":["spec",["html-nice",{"outputDir":"./reports/html-reports/","filename":"report.html","reportTitle":"Test Report Title","linkScreenshots":false,"showInBrowser":true,"collapseTests":false,"useOnAfterCommandForScreenshot":false}]],"services":["chromedriver"],"execArgv":[],"maxInstances":1,"maxInstancesPerCapability":100,"filesToWatch":[],"onPrepare":[null],"onWorkerStart":[],"onWorkerEnd":[],"before":[],"beforeSession":[],"beforeSuite":[],"beforeHook":[],"beforeTest":[],"beforeCommand":[],"afterCommand":[],"afterTest":[null],"afterHook":[],"afterSuite":[],"afterSession":[],"after":[],"onComplete":[null],"onReload":[],"automationProtocol":"webdriver"}},"retry":0,"failures":1,"retries":0,"end":"2022-12-02T17:29:56.941Z"},"metrics":{"passed":2,"skipped":2,"failed":1,"duration":23060,"start":"2022-12-02T17:29:33.881Z","end":"2022-12-02T17:29:56Z"},"title":"Test Report Title","suites":[{"type":"suite:start","start":"2022-12-02T17:29:33.891Z","_duration":22905,"tests":[{"type":"test","start":"2022-12-02T17:29:33.892Z","_duration":15929,"uid":"test-00-0","cid":"0-0","title":"providing the url-reg","fullTitle":"Launch the application.providing the url-reg","output":[],"retries":0,"parent":"Launch the application","state":"failed","events":[{"type":"Error","value":{"name":"Error","message":"Expect window to have title\n\nExpected: \u001b[32m\"Online \"\u001b[39m\nReceived: \u001b[31m\"Online \u001b[7mGifts Delivery: Buy/Send Gifts to India, Unique Gift Shop\u001b[27m\"\u001b[39m","stack":"Error: Expect window to have title\n\nExpected: \u001b[32m\"Online \"\u001b[39m\nReceived: \u001b[31m\"Online \u001b[7mGifts Delivery: Buy/Send Gifts to India, Unique Gift Shop\u001b[27m\"\u001b[39m\n    at Context.<anonymous> (C:\\Users\\RekhaR\\Desktop\\IGP\\test\\specs\\igp.js:11:31)\n    at process.processTicksAndRejections (node:internal/process/task_queues:95:5)","type":"Error"}}],"errorIndex":1,"end":"2022-12-02T17:29:49.821Z","errors":[{"name":"Error","message":"Expect window to have title\n\nExpected: \u001b[32m\"Online \"\u001b[39m\nReceived: \u001b[31m\"Online \u001b[7mGifts Delivery: Buy/Send Gifts to India, Unique Gift Shop\u001b[27m\"\u001b[39m","stack":"Error: Expect window to have title\n\nExpected: \u001b[32m\"Online \"\u001b[39m\nReceived: \u001b[31m\"Online \u001b[7mGifts Delivery: Buy/Send Gifts to India, Unique Gift Shop\u001b[27m\"\u001b[39m\n    at Context.<anonymous> (C:\\Users\\RekhaR\\Desktop\\IGP\\test\\specs\\igp.js:11:31)\n    at process.processTicksAndRejections (node:internal/process/task_queues:95:5)","type":"Error"}],"error":{"name":"Error","message":"Expect window to have title\n\nExpected: \u001b[32m\"Online \"\u001b[39m\nReceived: \u001b[31m\"Online \u001b[7mGifts Delivery: Buy/Send Gifts to India, Unique Gift Shop\u001b[27m\"\u001b[39m","stack":"Error: Expect window to have title\n\nExpected: \u001b[32m\"Online \"\u001b[39m\nReceived: \u001b[31m\"Online \u001b[7mGifts Delivery: Buy/Send Gifts to India, Unique Gift Shop\u001b[27m\"\u001b[39m\n    at Context.<anonymous> (C:\\Users\\RekhaR\\Desktop\\IGP\\test\\specs\\igp.js:11:31)\n    at process.processTicksAndRejections (node:internal/process/task_queues:95:5)","type":"Error"}},{"type":"test","start":"2022-12-02T17:29:49.822Z","_duration":4277,"uid":"test-00-1","cid":"0-0","title":"search the product in home page","fullTitle":"Launch the application.search the product in home page","output":[],"retries":0,"parent":"Launch the application","state":"passed","events":[],"errorIndex":0,"end":"2022-12-02T17:29:54.099Z"},{"type":"test","start":"2022-12-02T17:29:54.102Z","_duration":2690,"uid":"test-00-2","cid":"0-0","title":"using dynamic wait statements and checking the navigation to another page","fullTitle":"Launch the application.using dynamic wait statements and checking the navigation to another page","output":[],"retries":0,"parent":"Launch the application","state":"passed","events":[],"errorIndex":0,"end":"2022-12-02T17:29:56.792Z"},{"type":"test","start":"2022-12-02T17:29:56.795Z","_duration":0,"uid":"test-00-3","cid":"0-0","title":"select the product","fullTitle":"Launch the application.select the product","output":[],"retries":0,"parent":"Launch the application","state":"skipped"},{"type":"test","start":"2022-12-02T17:29:56.796Z","_duration":0,"uid":"test-00-4","cid":"0-0","title":"using dynamic wait statements and checking the navigation to another page","fullTitle":"Launch the application.using dynamic wait statements and checking the navigation to another page","output":[],"retries":0,"parent":"Launch the application","state":"skipped"}],"hooks":[],"suites":[],"hooksAndTests":[{"type":"test","start":"2022-12-02T17:29:33.892Z","_duration":15929,"uid":"test-00-0","cid":"0-0","title":"providing the url-reg","fullTitle":"Launch the application.providing the url-reg","output":[],"retries":0,"parent":"Launch the application","state":"failed","events":[{"type":"Error","value":{"name":"Error","message":"Expect window to have title\n\nExpected: \u001b[32m\"Online \"\u001b[39m\nReceived: \u001b[31m\"Online \u001b[7mGifts Delivery: Buy/Send Gifts to India, Unique Gift Shop\u001b[27m\"\u001b[39m","stack":"Error: Expect window to have title\n\nExpected: \u001b[32m\"Online \"\u001b[39m\nReceived: \u001b[31m\"Online \u001b[7mGifts Delivery: Buy/Send Gifts to India, Unique Gift Shop\u001b[27m\"\u001b[39m\n    at Context.<anonymous> (C:\\Users\\RekhaR\\Desktop\\IGP\\test\\specs\\igp.js:11:31)\n    at process.processTicksAndRejections (node:internal/process/task_queues:95:5)","type":"Error"}}],"errorIndex":1,"end":"2022-12-02T17:29:49.821Z","errors":[{"name":"Error","message":"Expect window to have title\n\nExpected: \u001b[32m\"Online \"\u001b[39m\nReceived: \u001b[31m\"Online \u001b[7mGifts Delivery: Buy/Send Gifts to India, Unique Gift Shop\u001b[27m\"\u001b[39m","stack":"Error: Expect window to have title\n\nExpected: \u001b[32m\"Online \"\u001b[39m\nReceived: \u001b[31m\"Online \u001b[7mGifts Delivery: Buy/Send Gifts to India, Unique Gift Shop\u001b[27m\"\u001b[39m\n    at Context.<anonymous> (C:\\Users\\RekhaR\\Desktop\\IGP\\test\\specs\\igp.js:11:31)\n    at process.processTicksAndRejections (node:internal/process/task_queues:95:5)","type":"Error"}],"error":{"name":"Error","message":"Expect window to have title\n\nExpected: \u001b[32m\"Online \"\u001b[39m\nReceived: \u001b[31m\"Online \u001b[7mGifts Delivery: Buy/Send Gifts to India, Unique Gift Shop\u001b[27m\"\u001b[39m","stack":"Error: Expect window to have title\n\nExpected: \u001b[32m\"Online \"\u001b[39m\nReceived: \u001b[31m\"Online \u001b[7mGifts Delivery: Buy/Send Gifts to India, Unique Gift Shop\u001b[27m\"\u001b[39m\n    at Context.<anonymous> (C:\\Users\\RekhaR\\Desktop\\IGP\\test\\specs\\igp.js:11:31)\n    at process.processTicksAndRejections (node:internal/process/task_queues:95:5)","type":"Error"}},{"type":"test","start":"2022-12-02T17:29:49.822Z","_duration":4277,"uid":"test-00-1","cid":"0-0","title":"search the product in home page","fullTitle":"Launch the application.search the product in home page","output":[],"retries":0,"parent":"Launch the application","state":"passed","events":[],"errorIndex":0,"end":"2022-12-02T17:29:54.099Z"},{"type":"test","start":"2022-12-02T17:29:54.102Z","_duration":2690,"uid":"test-00-2","cid":"0-0","title":"using dynamic wait statements and checking the navigation to another page","fullTitle":"Launch the application.using dynamic wait statements and checking the navigation to another page","output":[],"retries":0,"parent":"Launch the application","state":"passed","events":[],"errorIndex":0,"end":"2022-12-02T17:29:56.792Z"},{"type":"test","start":"2022-12-02T17:29:56.795Z","_duration":0,"uid":"test-00-3","cid":"0-0","title":"select the product","fullTitle":"Launch the application.select the product","output":[],"retries":0,"parent":"Launch the application","state":"skipped"},{"type":"test","start":"2022-12-02T17:29:56.796Z","_duration":0,"uid":"test-00-4","cid":"0-0","title":"using dynamic wait statements and checking the navigation to another page","fullTitle":"Launch the application.using dynamic wait statements and checking the navigation to another page","output":[],"retries":0,"parent":"Launch the application","state":"skipped"}],"uid":"suite-0-0","cid":"0-0","file":"C:\\Users\\RekhaR\\Desktop\\IGP\\test\\specs\\igp.js","title":"Launch the application","fullTitle":"Launch the application","parent":"","end":"2022-12-02T17:29:56.797Z"}],"reportFile":"C:\\Users\\RekhaR\\Desktop\\IGP\\reports\\html-reports\\report-0-0.html","browserName":"not specified"}